LICENSE
pnp/__init__.py
pnp/__main__.py
pnp/api/__init__.py
pnp/api/endpoints/__init__.py
pnp/api/endpoints/base.py
pnp/api/endpoints/catchall_route.py
pnp/api/endpoints/health.py
pnp/api/endpoints/log_level.py
pnp/api/endpoints/metrics.py
pnp/api/endpoints/ping.py
pnp/api/endpoints/trigger.py
pnp/api/endpoints/version.py
pnp/api/models.py
pnp/app.py
pnp/config/__init__.py
pnp/config/_base.py
pnp/config/_yaml.py
pnp/console/__init__.py
pnp/console/pnp.py
pnp/console/pnp_record_sound.py
pnp/engines/__init__.py
pnp/engines/_async.py
pnp/engines/_base.py
pnp/logging.py
pnp/logo.py
pnp/mocking.py
pnp/models.py
pnp/plugins/__init__.py
pnp/plugins/pull/__init__.py
pnp/plugins/pull/fitbit.py
pnp/plugins/pull/fs.py
pnp/plugins/pull/ftp.py
pnp/plugins/pull/gpio.py
pnp/plugins/pull/hass.py
pnp/plugins/pull/http.py
pnp/plugins/pull/monitor.py
pnp/plugins/pull/mqtt.py
pnp/plugins/pull/net.py
pnp/plugins/pull/presence.py
pnp/plugins/pull/sensor.py
pnp/plugins/pull/simple.py
pnp/plugins/pull/zway.py
pnp/plugins/push/__init__.py
pnp/plugins/push/fs.py
pnp/plugins/push/hass.py
pnp/plugins/push/http.py
pnp/plugins/push/ml.py
pnp/plugins/push/mqtt.py
pnp/plugins/push/notify.py
pnp/plugins/push/simple.py
pnp/plugins/push/storage.py
pnp/plugins/push/timedb.py
pnp/plugins/udf/__init__.py
pnp/plugins/udf/hass.py
pnp/plugins/udf/simple.py
pnp/runner.py
pnp/selector.py
pnp/shared/__init__.py
pnp/shared/async_.py
pnp/shared/exc.py
pnp/shared/gpio.py
pnp/shared/hass.py
pnp/shared/mqtt.py
pnp/shared/sound.py
pnp/shared/zipping.py
pnp/typing.py
pnp/utils.py
pnp/validator.py
pnp-0.28.0.dist-info/entry_points.txt
pnp-0.28.0.dist-info/LICENSE
pnp-0.28.0.dist-info/WHEEL
pnp-0.28.0.dist-info/METADATA
pnp-0.28.0.dist-info/RECORD
